MANIFEST.in
README.md
setup.py
data/__init__.py
data/parsers.py
data/services.py
rotten_tomatoes_cli.egg-info/PKG-INFO
rotten_tomatoes_cli.egg-info/SOURCES.txt
rotten_tomatoes_cli.egg-info/dependency_links.txt
rotten_tomatoes_cli.egg-info/entry_points.txt
rotten_tomatoes_cli.egg-info/requires.txt
rotten_tomatoes_cli.egg-info/top_level.txt
scripts/__init__.py
scripts/movies.py
scripts/rotten.py
scripts/search.py
scripts/tv.py
tables/__init__.py
tables/builders.py
tables/utilities.py
tables/rows/__init__.py
tables/rows/builders.py