Metadata-Version: 2.1
Name: rotten-tomatoes-cli
Version: 0.0.3
Summary: Rotten Tomatoes Command Line Tool
Home-page: https://github.com/jaebradley/rotten_tomatoes_cli
Author: Jae Bradley
Author-email: jae.b.bradley@gmail.com
License: UNKNOWN
Keywords: Movies,Rotten Tomatoes
Platform: UNKNOWN
Requires-Python: >=3.4
